prefect_saturn/__init__.py
prefect_saturn/_compat.py
prefect_saturn/core.py
prefect_saturn/messages.py
prefect_saturn/settings.py
prefect_saturn-0.6.0.dist-info/LICENSE
prefect_saturn-0.6.0.dist-info/METADATA
prefect_saturn-0.6.0.dist-info/WHEEL
prefect_saturn-0.6.0.dist-info/top_level.txt
prefect_saturn-0.6.0.dist-info/RECORD
