Metadata-Version: 2.1
Name: prefect-saturn
Version: 0.6.0
Summary: Client library for running Prefect Cloud flows in Saturn Cloud
Home-page: https://saturncloud.io/
Maintainer: Saturn Cloud Developers
Maintainer-email: open-source@saturncloud.io
License: BSD 3-clause
Project-URL: Issue Tracker, https://github.com/saturncloud/prefect-saturn/issues
Project-URL: Source, https://github.com/saturncloud/prefect-saturn
Project-URL: Documentation, http://docs.saturncloud.io
Keywords: dask,data-engineering,prefect,prefect-cloud,saturn-cloud,task-scheduling
Platform: UNKNOWN
Classifier: Development Status :: 3 - Alpha
Classifier: License :: OSI Approved :: BSD License
Classifier: Intended Audience :: Developers
Classifier: Intended Audience :: Science/Research
Classifier: Topic :: Scientific/Engineering
Classifier: Topic :: System :: Distributed Computing
Classifier: Programming Language :: Python
Classifier: Programming Language :: Python :: 3
Classifier: Programming Language :: Python :: 3.6
Classifier: Programming Language :: Python :: 3.7
Classifier: Programming Language :: Python :: 3.8
Requires-Python: >=3.6
Requires-Dist: cloudpickle
Requires-Dist: dask-saturn (>=0.0.4)
Requires-Dist: packaging
Requires-Dist: prefect (>0.13.0)
Requires-Dist: requests
Requires-Dist: ruamel.yaml
Provides-Extra: dev
Requires-Dist: cloudpickle ; extra == 'dev'
Requires-Dist: dask-saturn (>=0.0.4) ; extra == 'dev'
Requires-Dist: packaging ; extra == 'dev'
Requires-Dist: prefect (>0.13.0) ; extra == 'dev'
Requires-Dist: requests ; extra == 'dev'
Requires-Dist: ruamel.yaml ; extra == 'dev'
Requires-Dist: pytest ; extra == 'dev'
Requires-Dist: pytest-cov ; extra == 'dev'
Requires-Dist: responses ; extra == 'dev'
Provides-Extra: test
Requires-Dist: pytest ; extra == 'test'
Requires-Dist: pytest-cov ; extra == 'test'
Requires-Dist: responses ; extra == 'test'
